{
    "type": {
        "value": "feed"
    },
    "entry": [
        {
            "type": {
                "value": "feed"
            },
            "id": "QBS-NM000",
            "title": "The Personal History of David Copperfield",
            "summary": "",
            "content": {
                "type": "feed",
                "src": "general-provider://fetchData?type=FEED_JSON&url=aHR0cHM6Ly9yYXcuZ2l0aHVidXNlcmNvbnRlbnQuY29tL2plam1vb3JlL2oubW9vcmUtYXBwbGljYXN0ZXIuY29tL21hc3Rlci9RQlMlMjBGZWVkcy9OZXclMjBNb3ZpZXMvUUJTLUR1bW15LURDLmpzb24="
            },
            "media_group": [
                {
                    "type": "image",
                    "media_item": [
                        {
                            "type": "image",
                            "key": "image_base",
                            "src": "https://raw.githubusercontent.com/jejmoore/j.moore-applicaster.com/master/QBS%20Feeds/Assets/Movie%20Posters/dc.jpg"
                        }
                    ]
                }
            ]
        },
        {
            "type": {
                "value": "feed"
            },
            "id": "QBS-NM001",
            "title": "Big Hero 6",
            "summary": "",
            "content": {
                "type": "feed",
                "src": "general-provider://fetchData?type=FEED_JSON&url=aHR0cHM6Ly9yYXcuZ2l0aHVidXNlcmNvbnRlbnQuY29tL2plam1vb3JlL2oubW9vcmUtYXBwbGljYXN0ZXIuY29tL21hc3Rlci9RQlMlMjBGZWVkcy9OZXclMjBNb3ZpZXMvUUJTLUR1bW15LUJINi5qc29u"
            },
            "media_group": [
                {
                    "type": "image",
                    "media_item": [
                        {
                            "type": "image",
                            "key": "image_base",
                            "src": "https://raw.githubusercontent.com/jejmoore/j.moore-applicaster.com/master/QBS%20Feeds/Assets/Movie%20Posters/big-hero-6.jpg"
                        }
                    ]
                }
            ]
        },
        {
            "type": {
                "value": "feed"
            },
            "id": "QBS-NM002",
            "title": "Dunkirk",
            "summary": "",
            "content": {
                "type": "feed",
                "src": "general-provider://fetchData?type=FEED_JSON&url=aHR0cHM6Ly9yYXcuZ2l0aHVidXNlcmNvbnRlbnQuY29tL2plam1vb3JlL2oubW9vcmUtYXBwbGljYXN0ZXIuY29tL21hc3Rlci9RQlMlMjBGZWVkcy9OZXclMjBNb3ZpZXMvUUJTLUR1bW15LUR1bmtpcmsuanNvbg=="
            },
            "media_group": [
                {
                    "type": "image",
                    "media_item": [
                        {
                            "type": "image",
                            "key": "image_base",
                            "src": "https://raw.githubusercontent.com/jejmoore/j.moore-applicaster.com/master/QBS%20Feeds/Assets/Movie%20Posters/Dunkirk.png"
                        }
                    ]
                }
            ]
        },
        {
            "type": {
                "value": "feed"
            },
            "id": "QBS-NM003",
            "title": "Onward",
            "summary": "",
            "content": {
                "type": "feed",
                "src": "general-provider://fetchData?type=FEED_JSON&url=aHR0cHM6Ly9yYXcuZ2l0aHVidXNlcmNvbnRlbnQuY29tL2plam1vb3JlL2oubW9vcmUtYXBwbGljYXN0ZXIuY29tL21hc3Rlci9RQlMlMjBGZWVkcy9OZXclMjBNb3ZpZXMvUUJTLUR1bW15LU9ud2FyZC5qc29u"
            },
            "media_group": [
                {
                    "type": "image",
                    "media_item": [
                        {
                            "type": "image",
                            "key": "image_base",
                            "src": "https://raw.githubusercontent.com/jejmoore/j.moore-applicaster.com/master/QBS%20Feeds/Assets/Movie%20Posters/onward.jpg"
                        }
                    ]
                }
            ]
        }
    ],
    "author" : {
      "name" : "Applicaster"
    },
    "id" : "QBS-009",
    "title" : "New Movies",
    "description" : "Don’t miss these modern day classics!"
}
